[
{"name":"007 everything or nothing","developer":"sony","publisher":"sony computer entertainment","genre":"action adventure"},
{"name":"007 everything or nothing","developer":"electronic arts","publisher":"electronic arts","genre":"action adventure"},
{"name":"15 days","developer":"house of tales","publisher":"dtp entertainment","genre":"adventure"},
{"name":"1954 alcatraz","developer":"konami","publisher":"deep silver","genre":"adventure"},
{"name":"a hat in time","developer":"gears for breakfast","publisher":"humble bundle","genre":"platformer"},
{"name":"a new beginning","developer":"deadelic","publisher":"deep silver","genre":"adventure"},
{"name":"a plague tale innocence","developer":"asobo studio","publisher":"focus home interactive","genre":"action adventure"},
{"name":"a vampyre story","developer":"autumn moon","publisher":"crimson cow","genre":"adventure"},
{"name":"aer memories of old","developer":"through line","publisher":"square enix","genre":"action adventure"},
{"name":"afterfall insanity","developer":"nicholas interactive","publisher":"nicholas interactive","genre":"action adventure"},
{"name":"agatha","developer":"awe games","publisher":"unknown","genre":"adventure"},
{"name":"agatha christie hercule poirot the first cases","developer":"microids","publisher":"big ben interactive","genre":"adventure"},
{"name":"agatha christie the abc murders","developer":"koei","publisher":"koei","genre":"adventure"},
{"name":"agatha evil under the sun","developer":"awe games","publisher":"the adventure company","genre":"adventure"},
{"name":"agatha murder on the orient express","developer":"awe games","publisher":"the adventure company","genre":"adventure"},
{"name":"agatha murder on the orient express 2023","developer":"unknown","publisher":"microids","genre":"adventure"},
{"name":"agent a a puzzle in disguise","developer":"yak and co","publisher":"yak and co","genre":"puzzle"},
{"name":"agon 1","developer":"private moon studios","publisher":"mindie","genre":"adventure"},
{"name":"agon 2","developer":"private moon studios","publisher":"mindie","genre":"adventure"},
{"name":"agon 3","developer":"private moon studios","publisher":"mindie","genre":"adventure"},
{"name":"alan wake","developer":"remedy","publisher":"nordic games","genre":"action adventure"},
{"name":"alias","developer":"acclaim","publisher":"acclaim entertainment","genre":"action adventure"},
{"name":"alice the madness returns","developer":"unknown","publisher":"electronic arts","genre":"action adventure"},
{"name":"alone in the dark 4","developer":"eden games","publisher":"atari","genre":"action adventure"},
{"name":"alone in the dark illumination","developer":"spark","publisher":"atari","genre":"action adventure"},
{"name":"alternativa","developer":"first reality","publisher":"century","genre":"adventure"},
{"name":"american truck simulator","developer":"scs","publisher":"scs","genre":"racing"},
{"name":"amnesia the dark descent","developer":"nordic games","publisher":"frictional games","genre":"survival horror"},
{"name":"ankh","developer":"deck13","publisher":"bhv software","genre":"adventure"},
{"name":"ankh - heart of osiris","developer":"deck13","publisher":"bhv software","genre":"adventure"},
{"name":"annas quest","developer":"deadelic","publisher":"daedalic entertainment","genre":"adventure"},
{"name":"anno mutationem","developer":"unknown","publisher":"unknown","genre":"action adventure"},
{"name":"another code r","developer":"nintendo","publisher":"nintendo","genre":"adventure"},
{"name":"antichamber","developer":"unknown","publisher":"unknown","genre":"puzzle"},
{"name":"aporia beyond the valley","developer":"unknown","publisher":"unknown","genre":"adventure"},
{"name":"aqua moto racing utopia","developer":"dice","publisher":"electronic arts","genre":"racing"},
{"name":"archaica the path of light","developer":"bethesda","publisher":"bethesda","genre":"action adventure"},
{"name":"arise a simple story","developer":"piccolo","publisher":"techland publishing","genre":"action adventure"},
{"name":"arkhangel the house of the seven stars","developer":"sony","publisher":"sony computer entertainment","genre":"adventure"},
{"name":"art of murder cards of destiny","developer":"city interactive","publisher":"city interactive","genre":"adventure"},
{"name":"art of murder the hunt for the puppeteer","developer":"city interactive","publisher":"city interactive","genre":"adventure"},
{"name":"assassins creed","developer":"ubisoft","publisher":"ubisoft","genre":"action adventure"},
{"name":"assassins creed 3","developer":"ubisoft","publisher":"ubisoft","genre":"action adventure"},
{"name":"assassins creed black flag","developer":"ubisoft","publisher":"ubisoft","genre":"action adventure"},
{"name":"assassins creed brotherhood","developer":"ubisoft","publisher":"ubisoft","genre":"action adventure"},
{"name":"assassins creed liberation","developer":"ubisoft","publisher":"ubisoft","genre":"action adventure"},
{"name":"assassins creed odyssey","developer":"ubisoft","publisher":"ubisoft","genre":"action adventure"},
{"name":"assassins creed origins","developer":"ubisoft","publisher":"ubisoft","genre":"action adventure"},
{"name":"assassins creed revelations","developer":"ubisoft","publisher":"ubisoft","genre":"action adventure"},
{"name":"assassins creed syndicate","developer":"ubisoft","publisher":"ubisoft","genre":"action adventure"},
{"name":"assassins creed unity","developer":"ubisoft","publisher":"ubisoft","genre":"action adventure"},
{"name":"assassins creed valhalla","developer":"ubisoft","publisher":"ubisoft","genre":"action adventure"},
{"name":"assetto corsa competizione","developer":"kusos","publisher":"bandai namco entertainment","genre":"racing"},
{"name":"asterigos curse of the stars","developer":"tiny build","publisher":"acme game studios","genre":"action adventure"},
{"name":"astral chain","developer":"nintendo","publisher":"nintendo","genre":"action adventure"},
{"name":"automobilista 2","developer":"reiza studios","publisher":"reiza studios","genre":"racing"},
{"name":"baldo the guardian owls","developer":"unknown","publisher":"unknown","genre":"rpg"},
{"name":"batman arkham asylum","developer":"rocksteady","publisher":"eidos","genre":"action adventure"},
{"name":"batman arkham city","developer":"rocksteday","publisher":"eidos","genre":"action adventure"},
{"name":"batman arkham knight","developer":"rocksteady","publisher":"warner bros. interactive entertainment","genre":"action adventure"},
{"name":"batman arkham origins","developer":"konami","publisher":"deep silver","genre":"action adventure"},
{"name":"batman begins","developer":"sony","publisher":"electronic arts","genre":"action adventure"},
{"name":"batman begins","developer":"electronic arts","publisher":"electronic arts","genre":"action adventure"},
{"name":"batman brave bold game","developer":"nintendo","publisher":"nintendo","genre":"action adventure"},
{"name":"battle los angeles","developer":"ubisoft","publisher":"ubisoft","genre":"fps"},
{"name":"bayonetta","developer":"platinum games","publisher":"nintendo","genre":"action adventure"},
{"name":"bayonetta 2","developer":"platinum games","publisher":"nintendo","genre":"action adventure"},
{"name":"beyond good and evil","developer":"ubisoft","publisher":"ubisoft","genre":"action adventure"},
{"name":"beyond good and evil hd","developer":"sony","publisher":"sony computer entertainment","genre":"action adventure"},
{"name":"binary domain","developer":"amusement vision","publisher":"sega","genre":"action adventure"},
{"name":"bioshock infinite","developer":"2k games","publisher":"2k games","genre":"action adventure"},
{"name":"black sails - the ghost ship","developer":"deadelic","publisher":"daedalic entertainment","genre":"adventure"},
{"name":"blade runner","developer":"westwood studios","publisher":"virgin interactive","genre":"adventure"},
{"name":"blades of time","developer":"gaijin","publisher":"konami digital entertainment","genre":"action adventure"},
{"name":"blazing angels 2 secret missions of wwii","developer":"midway","publisher":"ubisoft","genre":"flightsim"},
{"name":"bloodrayne 2","developer":"terminal reality","publisher":"majesco entertainment","genre":"action adventure"},
{"name":"blue toad mystery files","developer":"blitz","publisher":"unknown","genre":"adventure"},
{"name":"book of unwritten tales","developer":"aspyr","publisher":"unknown","genre":"adventure"},
{"name":"botanicula","developer":"amanita design","publisher":"daedalic entertainment","genre":"platformer"},
{"name":"bound by flame","developer":"spider","publisher":"focus home interactive","genre":"action adventure"},
{"name":"brave","developer":"behaviour interactive","publisher":"disney interactive studios","genre":"action adventure"},
{"name":"brave","developer":"behaviour interactive","publisher":"disney interactive studios","genre":"action adventure"},
{"name":"broken pieces","developer":"elseware experience","publisher":"freedom games","genre":"action adventure"},
{"name":"broken sword 2. 5","developer":"revolution","publisher":"virgin interactive","genre":"adventure"},
{"name":"broken sword 5","developer":"revolution","publisher":"revolution","genre":"adventure"},
{"name":"broken sword circle of blood","developer":"revolution","publisher":"virgin interactive","genre":"adventure"},
{"name":"broken sword shadow of the templars","developer":"nintendo","publisher":"nintendo","genre":"adventure"},
{"name":"broken sword shadow of the templars directors cut","developer":"revolution","publisher":"revolution","genre":"adventure"},
{"name":"broken sword sleeping dragon","developer":"revolution","publisher":"thq","genre":"adventure"},
{"name":"broken sword smoking mirror","developer":"revolution","publisher":"virgin interactive","genre":"adventure"},
{"name":"broken sword the angel of death","developer":"revolution","publisher":"thq","genre":"adventure"},
{"name":"brothers - a tale of two sons","developer":"konami","publisher":"deep silver","genre":"action adventure"},
{"name":"brutal legend","developer":"double fine","publisher":"electronic arts","genre":"action adventure"},
{"name":"burnout 2","developer":"nintendo","publisher":"nintendo","genre":"action adventure"},
{"name":"call of cthulhu","developer":"headfirst productions","publisher":"bethesda","genre":"action adventure"},
{"name":"call of duty","developer":"infinity ward","publisher":"activision","genre":"fps"},
{"name":"call of duty - modern warfare 3","developer":"treyarch","publisher":"activision","genre":"fps"},
{"name":"call of duty 2","developer":"infinity ward","publisher":"activision","genre":"fps"},
{"name":"call of duty 4","developer":"infinty ward","publisher":"activision","genre":"fps"},
{"name":"call of duty 4 remastered","developer":"infinity ward","publisher":"activision","genre":"fps"},
{"name":"call of duty 5","developer":"infinty ward","publisher":"activision","genre":"fps"},
{"name":"call of duty 6","developer":"infinty ward","publisher":"activision","genre":"fps"},
{"name":"call of duty advanced warfare","developer":"sledgehamer","publisher":"activision","genre":"fps"},
{"name":"call of duty black ops","developer":"treyarch","publisher":"activision","genre":"fps"},
{"name":"call of duty black ops 3","developer":"treyarch","publisher":"activision","genre":"fps"},
{"name":"call of duty united offensive","developer":"infinity ward","publisher":"activision","genre":"fps"},
{"name":"call of the sea","developer":"out of the blue","publisher":"raw fury","genre":"adventure"},
{"name":"captain morgane and the golden turtle","developer":"bethesda","publisher":"reef entertainment","genre":"adventure"},
{"name":"cars 2","developer":"avalanche software","publisher":"disney interactive studios","genre":"action adventure"},
{"name":"castle of illusion","developer":"sega","publisher":"disney interactive studios","genre":"platformer"},
{"name":"castlevania lament of innocence","developer":"sony","publisher":"sony computer entertainment","genre":"action adventure"},
{"name":"castlevania lords of shadow","developer":"konami","publisher":"deep silver","genre":"action adventure"},
{"name":"catwomen","developer":"electronic arts","publisher":"nintendo","genre":"action adventure"},
{"name":"ceville","developer":"realmforge studios","publisher":"kalypso media","genre":"adventure"},
{"name":"chronicles of riddick dark athena","developer":"grin","publisher":"unknown","genre":"action adventure"},
{"name":"cleopatra a queens destiny","developer":"kheops","publisher":"nobilis","genre":"adventure"},
{"name":"code vein","developer":"bandai namco entertainment","publisher":"bandai namco entertainment","genre":"rpg"},
{"name":"cold fear","developer":"darkworks","publisher":"ubisoft","genre":"action adventure"},
{"name":"colin mcrae rally 2","developer":"codemasters","publisher":"codemasters","genre":"racing"},
{"name":"colin mcrae rally 2005","developer":"codemasters","publisher":"codemasters","genre":"racing"},
{"name":"contrast","developer":"compulsion games","publisher":"focus home interactive","genre":"platformer"},
{"name":"control","developer":"remedy","publisher":"505 games","genre":"action adventure"},
{"name":"crisis core final fantasy 7 reunion","developer":"toes software","publisher":"square enix","genre":"rpg"},
{"name":"cryostasis","developer":"aspyr","publisher":"unknown","genre":"fps"},
{"name":"crysis 2","developer":"crytek","publisher":"electronic arts","genre":"fps"},
{"name":"crysis 3","developer":"crytek","publisher":"electronic arts","genre":"fps"},
{"name":"cursed mountain","developer":"deep silver","publisher":"deep silver","genre":"adventure"},
{"name":"dakar desert rally","developer":"saber interactive","publisher":"embracer","genre":"racing"},
{"name":"damnation","developer":"blue omega","publisher":"codemasters","genre":"action adventure"},
{"name":"dark cloud 2","developer":"techland","publisher":"sony computer entertainment","genre":"rpg"},
{"name":"dark fall","developer":"darkling room","publisher":"the adventure company","genre":"adventure"},
{"name":"dark sector","developer":"digital extremes","publisher":"d3publisher","genre":"action adventure"},
{"name":"dark souls 3","developer":"from software","publisher":"bandai namco entertainment","genre":"action adventure"},
{"name":"dark void","developer":"airtight games","publisher":"capcom","genre":"action adventure"},
{"name":"darkness within","developer":"zoetrope interactive","publisher":"lighthouse interactive","genre":"adventure"},
{"name":"darksiders","developer":"vigil games","publisher":"thq","genre":"action adventure"},
{"name":"darksiders 2","developer":"vigil games","publisher":"thq","genre":"action adventure"},
{"name":"darksiders 3","developer":"gunfire games","publisher":"thq","genre":"action adventure"},
{"name":"darkwatch","developer":"techland","publisher":"ubisoft","genre":"fps"},
{"name":"day of the tentacle","developer":"lucas arts","publisher":"lucas arts","genre":"adventure"},
{"name":"dead island","developer":"techland","publisher":"deep silver","genre":"survival horror"},
{"name":"dead island riptide","developer":"eidos","publisher":"deep silver","genre":"action adventure"},
{"name":"dead or alive 2","developer":"tecmo","publisher":"acclaim entertainment","genre":"fighter"},
{"name":"dead space","developer":"visceral games","publisher":"electronic arts","genre":"action adventure"},
{"name":"dead space 3","developer":"visceral games","publisher":"electronic arts","genre":"survival horror"},
{"name":"dead space 3","developer":"visceral","publisher":"electronic arts","genre":"action adventure"},
{"name":"deadfall adventures","developer":"farm 51","publisher":"nordic games","genre":"action adventure"},
{"name":"deadlight","developer":"tequila works","publisher":"xbox game studios","genre":"platformer"},
{"name":"dear esther","developer":"the chinese room","publisher":"the chinese room","genre":"adventure"},
{"name":"demon stone","developer":"unknown","publisher":"atari","genre":"action adventure"},
{"name":"deponia","developer":"daedalic entertainment","publisher":"daedalic entertainment","genre":"adventure"},
{"name":"deponia 3","developer":"daedalic entertainment","publisher":"daedalic entertainment","genre":"adventure"},
{"name":"deponia doomsday","developer":"daedalic entertainment","publisher":"daedalic entertainment","genre":"adventure"},
{"name":"destination treasure island","developer":"unknown","publisher":"unknown","genre":"adventure"},
{"name":"deus ex human revolution","developer":"eidos","publisher":"eidos","genre":"action adventure"},
{"name":"devil may cry","developer":"capcom","publisher":"capcom","genre":"action adventure"},
{"name":"devil may cry 2","developer":"capcom","publisher":"capcom","genre":"action adventure"},
{"name":"devil may cry 3","developer":"capcom","publisher":"capcom","genre":"action adventure"},
{"name":"devil may cry 4","developer":"capcom","publisher":"capcom","genre":"action adventure"},
{"name":"devil may cry 5","developer":"capcom","publisher":"capcom","genre":"action adventure"},
{"name":"devil may cry dmc","developer":"ninja theory","publisher":"capcom","genre":"action adventure"},
{"name":"diamon jones - amulet of the world","developer":"big fish","publisher":"unknown","genre":"adventure"},
{"name":"dirt","developer":"codemasters","publisher":"codemasters","genre":"racing"},
{"name":"dirt 2","developer":"codemasters","publisher":"codemasters","genre":"racing"},
{"name":"dirt 3","developer":"codemasters","publisher":"codemasters","genre":"racing"},
{"name":"dirt 4","developer":"codemasters","publisher":"codemasters","genre":"racing"},
{"name":"dirt rally","developer":"codemasters","publisher":"codemasters","genre":"racing"},
{"name":"dishonored","developer":"arkane studios","publisher":"bethesda","genre":"action adventure"},
{"name":"dishonored 2","developer":"arkane studios","publisher":"bethesda","genre":"action adventure"},
{"name":"distance","developer":"tequilla","publisher":"big ben interactive","genre":"racing"},
{"name":"donkey kong country returns","developer":"nintendo","publisher":"nintendo","genre":"platformer"},
{"name":"dorian grey","developer":"unknown","publisher":"unknown","genre":"adventure"},
{"name":"dracula","developer":"dreamcatcher","publisher":"unknown","genre":"adventure"},
{"name":"dracula 4 the shadow of the dragon","developer":"unknown","publisher":"microids","genre":"adventure"},
{"name":"dragon age 2","developer":"bioware","publisher":"electronic arts","genre":"rpg"},
{"name":"dragon age 3","developer":"bioware","publisher":"electronic arts","genre":"rpg"},
{"name":"dragon quest 8","developer":"sony","publisher":"sony computer entertainment","genre":"rpg"},
{"name":"dragon quest heroes","developer":"koei","publisher":"koei","genre":"rpg"},
{"name":"dragons dogma dark arisen","developer":"capcom","publisher":"capcom","genre":"rpg"},
{"name":"dragons lair","developer":"nintendo","publisher":"nintendo","genre":"action adventure"},
{"name":"dreamfall chapters","developer":"red thread games","publisher":"deep silver","genre":"adventure"},
{"name":"dreamfall the longest journey","developer":"aspyr","publisher":"funcom","genre":"adventure"},
{"name":"driver san francisco","developer":"techland","publisher":"deep silver","genre":"racing"},
{"name":"dtm race driver 3","developer":"codemasters","publisher":"codemasters","genre":"racing"},
{"name":"dyad","developer":"right square bracket left square bracket","publisher":"right square bracket left square bracket","genre":"racing"},
{"name":"dying light","developer":"techland","publisher":"warner bros. interactive entertainment","genre":"action adventure"},
{"name":"earth defense force insect armageddon","developer":"viscous studioy","publisher":"eidos","genre":"action adventure"},
{"name":"eastshade","developer":"eastshade studios","publisher":"eastshade studios","genre":"adventure"},
{"name":"eastward","developer":"pixpil","publisher":"chucklefish","genre":"action adventure"},
{"name":"echo","developer":"kheops","publisher":"the adventure company","genre":"adventure"},
{"name":"elex","developer":"piranha bytes","publisher":"thq","genre":"action adventure"},
{"name":"en garde","developer":"unknown","publisher":"unknown","genre":"action adventure"},
{"name":"enslaved odyssey to the west","developer":"ninja theory","publisher":"konami digital entertainment","genre":"action adventure"},
{"name":"epic mickey","developer":"nintendo","publisher":"disney interactive studios","genre":"action adventure"},
{"name":"epitasis","developer":"sony","publisher":"sony computer entertainment","genre":"adventure"},
{"name":"eragon","developer":"stormfront studios","publisher":"vivendi games","genre":"action adventure"},
{"name":"ethernal darkness","developer":"nintendo","publisher":"nintendo","genre":"action adventure"},
{"name":"euro truck simulator 2","developer":"scs","publisher":"scs","genre":"racing"},
{"name":"ever forward","developer":"pathea games","publisher":"pm studios","genre":"puzzle"},
{"name":"everybody is gone to the rapture","developer":"chinese room","publisher":"chinese room","genre":"adventure"},
{"name":"eye of isis","developer":"unknown","publisher":"unknown","genre":"action adventure"},
{"name":"f1 2012","developer":"codemasters","publisher":"codemasters","genre":"racing"},
{"name":"fable 3","developer":"lionhead","publisher":"microsoft","genre":"action adventure"},
{"name":"face noir","developer":"mad orange","publisher":"daedalic entertainment","genre":"adventure"},
{"name":"fallout 4","developer":"bethesda","publisher":"bethesda","genre":"rpg"},
{"name":"far cry 2","developer":"ubisoft","publisher":"ubisoft","genre":"fps"},
{"name":"far lone sails","developer":"through line","publisher":"square enix","genre":"puzzle"},
{"name":"fast racing neo","developer":"nintendo","publisher":"nintendo","genre":"racing"},
{"name":"figment","developer":"bedtime digital game","publisher":"bedtime digital game","genre":"puzzle"},
{"name":"firewatch","developer":"campo santo","publisher":"panic","genre":"adventure"},
{"name":"flatout ultimate carnage","developer":"bug bear","publisher":"empire interactive","genre":"racing"},
{"name":"flower","developer":"thatgamecompany","publisher":"sony computer entertainment","genre":"action adventure"},
{"name":"flushed away","developer":"nintendo","publisher":"d3publisher","genre":"action adventure"},
{"name":"flying tigers shadows over china","developer":"codemasters","publisher":"codemasters","genre":"racing"},
{"name":"flyn","developer":"studio thunderhorse","publisher":"humble games","genre":"platformer"},
{"name":"forgotton anne","developer":"throughline games","publisher":"square enix","genre":"puzzle"},
{"name":"formula fusion","developer":"electronic arts","publisher":"electronic arts","genre":"racing"},
{"name":"formula one 2010","developer":"codemasters","publisher":"codemasters","genre":"racing"},
{"name":"forza horizon 4","developer":"turn 10","publisher":"microsoft","genre":"racing"},
{"name":"forza motorsport 4","developer":"turn 10","publisher":"microsoft","genre":"racing"},
{"name":"fragile dreams","developer":"nintendo","publisher":"nintendo","genre":"adventure"},
{"name":"freezeme","developer":"bethesda","publisher":"bethesda","genre":"platformer"},
{"name":"fuel","developer":"asobo studio","publisher":"codemasters","genre":"racing"},
{"name":"full throttle","developer":"lucas arts","publisher":"lucas arts","genre":"adventure"},
{"name":"gabriel knight sins of the fathers","developer":"unknown","publisher":"unknown","genre":"adventure"},
{"name":"gears of war","developer":"epic games","publisher":"xbox game studios","genre":"action adventure"},
{"name":"genji dawn of the samurai","developer":"game republic","publisher":"sony computer entertainment","genre":"action adventure"},
{"name":"genji days of the blade","developer":"sony","publisher":"sony computer entertainment","genre":"action adventure"},
{"name":"ghost hunter","developer":"techland","publisher":"deep silver","genre":"action adventure"},
{"name":"ghost in the shell - stand alone complex","developer":"sony","publisher":"sony computer entertainment","genre":"action adventure"},
{"name":"ghost of a tale","developer":"milestone","publisher":"milestone","genre":"action adventure"},
{"name":"ghost pirates of vooju island","developer":"autumn moon entertainment","publisher":"dtp entertainment","genre":"adventure"},
{"name":"gladiator - sword of vengeance","developer":"unknown","publisher":"acclaim entertainment","genre":"action adventure"},
{"name":"god eater 3","developer":"gunfire games","publisher":"bandai namco entertainment","genre":"action adventure"},
{"name":"god hand","developer":"sony","publisher":"capcom","genre":"fighter"},
{"name":"god mode","developer":"saber interactive","publisher":"atlus","genre":"action adventure"},
{"name":"god of war","developer":"santa monica studio","publisher":"sony computer entertainment","genre":"action adventure"},
{"name":"god of war 2","developer":"santa monica studio","publisher":"sony computer entertainment","genre":"action adventure"},
{"name":"golden axe beast rider","developer":"secret level","publisher":"sega","genre":"action adventure"},
{"name":"gran turismo 2","developer":"polyphony digital","publisher":"sony computer entertainment","genre":"racing"},
{"name":"gran turismo 3","developer":"polyphony digital","publisher":"sony computer entertainment","genre":"racing"},
{"name":"gran turismo 4","developer":"polyphony digital","publisher":"sony computer entertainment","genre":"racing"},
{"name":"gran turismo 5","developer":"polyphony digital","publisher":"sony computer entertainment","genre":"racing"},
{"name":"gran turismo 6","developer":"polyphony digital","publisher":"sony computer entertainment","genre":"action adventure"},
{"name":"granblue fantasy relink","developer":"cygames","publisher":"cygames","genre":"rpg"},
{"name":"gravel","developer":"milestone","publisher":"milestone","genre":"racing"},
{"name":"gray matter","developer":"wizarbox","publisher":"dtp entertainment","genre":"adventure"},
{"name":"greedfall","developer":"spider","publisher":"focus home interactive","genre":"rpg"},
{"name":"grid","developer":"codemasters","publisher":"codemasters","genre":"racing"},
{"name":"grid 2","developer":"codemasters","publisher":"codemasters","genre":"racing"},
{"name":"grid autosport","developer":"codemasters","publisher":"codemasters","genre":"racing"},
{"name":"grim fandango remastered","developer":"lucas arts","publisher":"unknown","genre":"adventure"},
{"name":"gun","developer":"neversoft","publisher":"activision","genre":"action adventure"},
{"name":"gun","developer":"neversoft","publisher":"activision","genre":"action adventure"},
{"name":"gylt","developer":"tequila","publisher":"tequila","genre":"action adventure"},
{"name":"half-life 2","developer":"valve","publisher":"valve","genre":"action adventure"},
{"name":"half-life 2 episode one","developer":"valve","publisher":"valve","genre":"action adventure"},
{"name":"half-life 2 episode two","developer":"valve","publisher":"valve","genre":"action adventure"},
{"name":"harry potter and the deathly hollows","developer":"electronic arts","publisher":"electronic arts","genre":"action adventure"},
{"name":"haunted","developer":"hmh","publisher":"deck 13","genre":"adventure"},
{"name":"haven call of the king","developer":"techland","publisher":"deep silver","genre":"action adventure"},
{"name":"heaven","developer":"techland","publisher":"deep silver","genre":"adventure"},
{"name":"heavenly sword","developer":"sony","publisher":"sony computer entertainment","genre":"action adventure"},
{"name":"hellblade senuas sacrifice","developer":"ninja theory","publisher":"ninja theory","genre":"action adventure"},
{"name":"heroes over europe","developer":"transmission games","publisher":"ubisoft","genre":"flightsim"},
{"name":"hob","developer":"runic games","publisher":"runic games","genre":"action adventure"},
{"name":"horizon zero dawn","developer":"guerilia","publisher":"sony computer entertainment","genre":"action adventure"},
{"name":"hunted demon forge","developer":"inxile entertainment","publisher":"bethesda","genre":"action adventure"},
{"name":"hydro thunder","developer":"midway games","publisher":"sega","genre":"racing"},
{"name":"hydrophobia prophecy","developer":"dark energy digital","publisher":"microsoft","genre":"action adventure"},
{"name":"i am alive","developer":"ubisoft","publisher":"ubisoft","genre":"action adventure"},
{"name":"i ninja","developer":"capcom","publisher":"unknown","genre":"platformer"},
{"name":"ice age 2","developer":"blue sky studios","publisher":"sierra","genre":"platformer"},
{"name":"ico","developer":"sony","publisher":"sony computer entertainment","genre":"action adventure"},
{"name":"immortals fenyx rising","developer":"ubisoft","publisher":"ubisoft","genre":"action adventure"},
{"name":"inazuma eleven strikers","developer":"nintendo","publisher":"nintendo","genre":"sports"},
{"name":"indiana jones and the emperors tomb","developer":"lucasarts","publisher":"unknown","genre":"platformer"},
{"name":"indiana jones and the staff of kings","developer":"sony","publisher":"activision","genre":"action adventure"},
{"name":"indivisible","developer":"polygon treehouse","publisher":"polygon treehouse","genre":"action adventure"},
{"name":"infra","developer":"loiste interactive","publisher":"loiste interactive","genre":"adventure"},
{"name":"inversion","developer":"saber interactive","publisher":"bandai namco entertainment","genre":"action adventure"},
{"name":"jack keane","developer":"deck 13","publisher":"kalypso media","genre":"adventure"},
{"name":"jack keane 2 the fire within","developer":"deck 13","publisher":"nordic games","genre":"adventure"},
{"name":"jack orlando directors cut","developer":"unknown","publisher":"wl bowl software","genre":"adventure"},
{"name":"jack the ripper","developer":"unknown","publisher":"the adventure company","genre":"adventure"},
{"name":"jak and dexter 2","developer":"naughty dog","publisher":"sony computer entertainment","genre":"action adventure"},
{"name":"jak and dexter 3","developer":"naughty dog","publisher":"sony computer entertainment","genre":"action adventure"},
{"name":"jak and dexter the precursor legacy","developer":"naughty dog","publisher":"sony computer entertainment","genre":"action adventure"},
{"name":"james bond bloodstone","developer":"bizarre creations","publisher":"activision","genre":"action adventure"},
{"name":"jekyll and hyde 2010","developer":"unknown","publisher":"bitcomposer games","genre":"adventure"},
{"name":"jet set  radio","developer":"unknown","publisher":"sega","genre":"action adventure"},
{"name":"journey","developer":"thatgamecompany","publisher":"sony computer entertainment","genre":"action adventure"},
{"name":"journey","developer":"thatgamecompany","publisher":"sony computer entertainment","genre":"action adventure"},
{"name":"jusant","developer":"dont nod","publisher":"unknown","genre":"platformer"},
{"name":"kane and lynch dead men","developer":"ko interactive","publisher":"eidos","genre":"action adventure"},
{"name":"keepsake","developer":"unknown","publisher":"the adventure company","genre":"adventure"},
{"name":"kena bridge of spirits","developer":"klyton","publisher":"big ben interactive","genre":"action adventure"},
{"name":"killer 7","developer":"sony","publisher":"sony computer entertainment","genre":"action adventure"},
{"name":"king kong the game","developer":"unknown","publisher":"ubisoft","genre":"action adventure"},
{"name":"kingdom hearts","developer":"square enix","publisher":"square enix","genre":"rpg"},
{"name":"kingdom hearts 2","developer":"square enix","publisher":"square enix","genre":"rpg"},
{"name":"kingdoms of amalur reckoning","developer":"big huge","publisher":"electronic arts","genre":"action adventure"},
{"name":"kirbys epic yarn","developer":"nintendo","publisher":"nintendo","genre":"platformer"},
{"name":"kona","developer":"koei","publisher":"koei","genre":"adventure"},
{"name":"kulaworld","developer":"game design sweden ab","publisher":"sony computer entertainment","genre":"puzzle"},
{"name":"kung fu panda","developer":"luxoflux","publisher":"activision","genre":"platformer"},
{"name":"kya dark lineage","developer":"eden games","publisher":"eden","genre":"action adventure"},
{"name":"la noire","developer":"team bondi","publisher":"rockstar","genre":"action adventure"},
{"name":"lake ridden","developer":"through line","publisher":"square enix","genre":"action adventure"},
{"name":"largo winch","developer":"dupuis","publisher":"ubisoft","genre":"adventure"},
{"name":"left4dead","developer":"valve","publisher":"unknown","genre":"fps"},
{"name":"legend of kay anniversary","developer":"nordic games","publisher":"nordic games","genre":"action adventure"},
{"name":"legend of spyro a new beginning","developer":"nintendo","publisher":"nintendo","genre":"action adventure"},
{"name":"legendary","developer":"spark","publisher":"gamecock media group","genre":"fps"},
{"name":"lego batman 2","developer":"remedy","publisher":"sega","genre":"action adventure"},
{"name":"lego lord of the rings","developer":"travellers tales","publisher":"thq","genre":"platformer"},
{"name":"lego marvel super heroes","developer":"travellers tales","publisher":"warner bros. interactive entertainment","genre":"action adventure"},
{"name":"lego pirates of the caribbean","developer":"travellers tales","publisher":"disney interactive studios","genre":"platformer"},
{"name":"lego star wars the skywalker saga","developer":"travellers tales","publisher":"disney interactive studios","genre":"action adventure"},
{"name":"lego starwars 1","developer":"travellers tales","publisher":"thq","genre":"action adventure"},
{"name":"lego starwars 2","developer":"travellers tales","publisher":"thq","genre":"action adventure"},
{"name":"lemony snickets a series of unfortunate events","developer":"nintendo","publisher":"nintendo","genre":"action adventure"},
{"name":"life is strange","developer":"dont nod","publisher":"square enix","genre":"adventure"},
{"name":"lightning returns final fantasy 13","developer":"square enix","publisher":"square enix","genre":"rpg"},
{"name":"loch ness","developer":"unknown","publisher":"wanadoa","genre":"adventure"},
{"name":"lord of the rings - war in the north","developer":"electronic arts","publisher":"electronic arts","genre":"action adventure"},
{"name":"lost chronicles of zerzura","developer":"cranberry production","publisher":"dtp entertainment","genre":"adventure"},
{"name":"lost horizon","developer":"animation arts","publisher":"deep silver","genre":"adventure"},
{"name":"lost horizon 2","developer":"animation arts","publisher":"deep silver","genre":"adventure"},
{"name":"lost planet","developer":"capcom","publisher":"capcom","genre":"action adventure"},
{"name":"lost planet 2","developer":"capcom","publisher":"capcom","genre":"action adventure"},
{"name":"lost planet 3","developer":"spark","publisher":"capcom","genre":"action adventure"},
{"name":"lotr return of the king","developer":"electronic arts","publisher":"electronic arts","genre":"action adventure"},
{"name":"luigis mansion","developer":"nintendo","publisher":"nintendo","genre":"action adventure"},
{"name":"luigis mansion 3","developer":"nintendo","publisher":"nintendo","genre":"action adventure"},
{"name":"luna the shadow dust","developer":"unknown","publisher":"unknown","genre":"adventure"},
{"name":"mad max","developer":"avalanche studios","publisher":"warner bros. interactive entertainment","genre":"action adventure"},
{"name":"mafia 2","developer":"unknown","publisher":"unknown","genre":"action adventure"},
{"name":"magrunner dark pulse","developer":"3am","publisher":"focus home interactive","genre":"action adventure"},
{"name":"majin and the forsaken kingdom","developer":"sony","publisher":"bandai namco entertainment","genre":"action adventure"},
{"name":"mario kart double dash","developer":"nintendo","publisher":"nintendo","genre":"racing"},
{"name":"mariokart 8","developer":"nintendo","publisher":"nintendo","genre":"action adventure"},
{"name":"mark of the ninja","developer":"klei entertainment","publisher":"xbox game studios","genre":"platformer"},
{"name":"marvels guardians of the galaxy","developer":"eidos","publisher":"square enix","genre":"action adventure"},
{"name":"mass effect","developer":"bioware","publisher":"electronic arts","genre":"rpg"},
{"name":"mass effect 2","developer":"bioware","publisher":"electronic arts","genre":"rpg"},
{"name":"mass effect 3","developer":"bioware","publisher":"electronic arts","genre":"action adventure"},
{"name":"mass effect andromeda","developer":"bioware","publisher":"electronic arts","genre":"action adventure"},
{"name":"mass effect legendary edition","developer":"bioware","publisher":"electronic arts","genre":"action adventure"},
{"name":"mata hari","developer":"cranberry","publisher":"dtp entertainment","genre":"adventure"},
{"name":"maximo ghosts to glory","developer":"sony","publisher":"sony computer entertainment","genre":"action adventure"},
{"name":"maximo vs army of zin","developer":"sony","publisher":"capcom","genre":"action adventure"},
{"name":"medal of honor breakthrough","developer":"unknown","publisher":"activision","genre":"fps"},
{"name":"memento mori","developer":"unknown","publisher":"dtp entertainment","genre":"adventure"},
{"name":"memoranda","developer":"dice","publisher":"electronic arts","genre":"adventure"},
{"name":"metro 2033","developer":"4a games","publisher":"thq","genre":"fps"},
{"name":"metro last light","developer":"techland","publisher":"deep silver","genre":"action adventure"},
{"name":"metroid other m","developer":"nintendo","publisher":"nintendo","genre":"action adventure"},
{"name":"metroid prime echos","developer":"nintendo","publisher":"nintendo","genre":"action adventure"},
{"name":"metropolis street racer","developer":"bizarre creations","publisher":"sega","genre":"racing"},
{"name":"mirrors edge","developer":"dice","publisher":"electronic arts","genre":"platformer"},
{"name":"mirrors edge catalyst","developer":"dice","publisher":"electronic arts","genre":"platformer"},
{"name":"moa pacific assault","developer":"danger close games","publisher":"electronic arts","genre":"fps"},
{"name":"moha airborne","developer":"danger close games","publisher":"electronic arts","genre":"fps"},
{"name":"moha allied assault","developer":"2015 inc","publisher":"electronic arts","genre":"fps"},
{"name":"monkey island 3","developer":"lucas arts","publisher":"lucas arts","genre":"adventure"},
{"name":"monkey island 4","developer":"lucas arts","publisher":"lucas arts","genre":"adventure"},
{"name":"monster hunter tri","developer":"nintendo","publisher":"nintendo","genre":"action adventure"},
{"name":"motogp 13","developer":"milestone","publisher":"unknown","genre":"racing"},
{"name":"motogp 3","developer":"unknown","publisher":"thq","genre":"racing"},
{"name":"motorstorm artic escape","developer":"nintendo","publisher":"nintendo","genre":"racing"},
{"name":"motorstorm pacific rift","developer":"sony","publisher":"sony computer entertainment","genre":"action adventure"},
{"name":"mozart","developer":"first reality","publisher":"century","genre":"adventure"},
{"name":"ms splosion man","developer":"unknown","publisher":"unknown","genre":"platformer"},
{"name":"naruto clash of ninja revolution","developer":"nintendo","publisher":"nintendo","genre":"action adventure"},
{"name":"nascar racing 2003","developer":"sierra","publisher":"unknown","genre":"racing"},
{"name":"nba live 2005","developer":"ea vancouver","publisher":"electronic arts","genre":"sports"},
{"name":"nd creature of kapu cave","developer":"her interactive","publisher":"her interactive","genre":"adventure"},
{"name":"nd curse of blackmoor","developer":"her interactive","publisher":"her interactive","genre":"adventure"},
{"name":"nd danger by design","developer":"her interactive","publisher":"her interactive","genre":"adventure"},
{"name":"nd danger on deception island","developer":"her interactive","publisher":"her interactive","genre":"adventure"},
{"name":"nd ghost dogs of moon lake","developer":"her interactive","publisher":"her interactive","genre":"adventure"},
{"name":"nd ghost of thornton hall","developer":"her interactive","publisher":"her interactive","genre":"adventure"},
{"name":"nd last train to the blue moon canyon","developer":"her interactive","publisher":"her interactive","genre":"adventure"},
{"name":"nd legend of the crystal skull","developer":"her interactive","publisher":"her interactive","genre":"adventure"},
{"name":"nd sea of darkness","developer":"her interactive","publisher":"her interactive","genre":"adventure"},
{"name":"nd secret of the old clock","developer":"her interactive","publisher":"her interactive","genre":"adventure"},
{"name":"nd secret of the scarlet hand","developer":"her interactive","publisher":"her interactive","genre":"adventure"},
{"name":"nd secret of the scarlet hand","developer":"her interactive","publisher":"her interactive","genre":"adventure"},
{"name":"nd secrets can kill","developer":"her interactive","publisher":"her interactive","genre":"adventure"},
{"name":"nd shadow ranch - sha-full","developer":"her interactive","publisher":"her interactive","genre":"adventure"},
{"name":"nd the captive curse","developer":"her interactive","publisher":"her interactive","genre":"adventure"},
{"name":"nd the phantom of venice","developer":"her interactive","publisher":"her interactive","genre":"adventure"},
{"name":"nd the secret of shadow ranch","developer":"her interactive","publisher":"her interactive","genre":"adventure"},
{"name":"nd the silent spy","developer":"her interactive","publisher":"her interactive","genre":"adventure"},
{"name":"nd the white wolf of icicle creek","developer":"her interactive","publisher":"her interactive","genre":"adventure"},
{"name":"nd tomb of the lost queen","developer":"her interactive","publisher":"her interactive","genre":"adventure"},
{"name":"nd treasure in the royal tower","developer":"her interactive","publisher":"her interactive","genre":"adventure"},
{"name":"nd warnings at waverly academy","developer":"her interactive","publisher":"her interactive","genre":"adventure"},
{"name":"need for speed hot pursuit","developer":"blitz","publisher":"electronic arts","genre":"racing"},
{"name":"need for speed pro street","developer":"grin","publisher":"electronic arts","genre":"racing"},
{"name":"need for speed the run","developer":"black box","publisher":"electronic arts","genre":"racing"},
{"name":"nfs most wanted","developer":"criterion","publisher":"electronic arts","genre":"racing"},
{"name":"nfs most wanted 2012","developer":"criterion","publisher":"electronic arts","genre":"racing"},
{"name":"nfs rivals","developer":"electronic arts","publisher":"electronic arts","genre":"racing"},
{"name":"nfs shift","developer":"slightly mad","publisher":"electronic arts","genre":"racing"},
{"name":"nfs shift 2","developer":"slightly mad","publisher":"electronic arts","genre":"racing"},
{"name":"ni no kuni 2","developer":"level 5","publisher":"bandai namco entertainment","genre":"rpg"},
{"name":"nibiru","developer":"future games","publisher":"the adventure company","genre":"adventure"},
{"name":"nick bounty and the dame with the blue chewed shoe","developer":"respawn","publisher":"electronic arts","genre":"adventure"},
{"name":"nier automata","developer":"platinum","publisher":"square enix","genre":"action adventure"},
{"name":"nights journey of dreams","developer":"nintendo","publisher":"nintendo","genre":"action adventure"},
{"name":"nikopol - secrets of the immortals","developer":"unknown","publisher":"microids","genre":"adventure"},
{"name":"ninja blade","developer":"from software","publisher":"microsoft","genre":"action adventure"},
{"name":"nioh complete edition","developer":"koei","publisher":"koei","genre":"action adventure"},
{"name":"no mans sky","developer":"hello games","publisher":"sony computer entertainment","genre":"rpg"},
{"name":"no more heroes","developer":"grasshoper","publisher":"rising star games","genre":"action adventure"},
{"name":"nostradamus","developer":"kheops","publisher":"the adventure company","genre":"adventure"},
{"name":"obduction","developer":"cyan","publisher":"cyan","genre":"adventure"},
{"name":"obscure","developer":"mighty rocket studio","publisher":"mc2 entertainment","genre":"action adventure"},
{"name":"obscure 2","developer":"mighty rocket studio","publisher":"mc2 entertainment","genre":"survival horror"},
{"name":"observer","developer":"bloober team","publisher":"aspyr","genre":"adventure"},
{"name":"okami","developer":"sony","publisher":"capcom","genre":"action adventure"},
{"name":"onimusha 2","developer":"sony","publisher":"sony computer entertainment","genre":"action adventure"},
{"name":"onimusha 3","developer":"capcom","publisher":"capcom","genre":"action adventure"},
{"name":"onimusha 3","developer":"capcom","publisher":"capcom","genre":"action adventure"},
{"name":"ori and the blind forest","developer":"moon studios","publisher":"xbox game studios","genre":"platformer"},
{"name":"oure","developer":"koei","publisher":"koei","genre":"action adventure"},
{"name":"outrun 2006","developer":"sumo digital","publisher":"sega","genre":"racing"},
{"name":"oxenfree 2 lost signals","developer":"nightschool","publisher":"netflix","genre":"adventure"},
{"name":"p.n.03","developer":"nintendo","publisher":"nintendo","genre":"action adventure"},
{"name":"painkiller","developer":"people can fly","publisher":"dreamcatcher interactive","genre":"fps"},
{"name":"pandoras tower","developer":"nintendo","publisher":"nintendo","genre":"rpg"},
{"name":"paradise","developer":"white birds productions","publisher":"ubisoft","genre":"adventure"},
{"name":"penumbra black plague","developer":"unknown","publisher":"paradox interactive","genre":"action adventure"},
{"name":"pirates of the caribbean","developer":"akella","publisher":"bethesda","genre":"action adventure"},
{"name":"pirates of the caribbean - at worlds end","developer":"unknown","publisher":"disney interactive studios","genre":"action adventure"},
{"name":"pitfall","developer":"sony","publisher":"sony computer entertainment","genre":"action adventure"},
{"name":"pitfall the lost expedition","developer":"infinty ward","publisher":"activision","genre":"platformer"},
{"name":"planet of lana","developer":"wishfully","publisher":"thunderful","genre":"platformer"},
{"name":"prey","developer":"human head studios","publisher":"2k games","genre":"action adventure"},
{"name":"primal","developer":"sony","publisher":"sony computer entertainment","genre":"action adventure"},
{"name":"prince of persia 2008","developer":"ubisoft","publisher":"ubisoft","genre":"platformer"},
{"name":"prince of persia forgotten sands","developer":"ubisoft","publisher":"ubisoft","genre":"action adventure"},
{"name":"prince of persia sands of time","developer":"ubisoft","publisher":"ubisoft","genre":"action adventure"},
{"name":"prince of persia two thrones","developer":"ubisoft","publisher":"ubisoft","genre":"action adventure"},
{"name":"prince of persia warrior within","developer":"ubisoft","publisher":"ubisoft","genre":"action adventure"},
{"name":"project cars","developer":"slightly mad","publisher":"slightly mad studios","genre":"racing"},
{"name":"project cars 2","developer":"slightly mad","publisher":"bandai namco entertainment","genre":"racing"},
{"name":"project cars 3","developer":"slightly mad","publisher":"bandai namco entertainment","genre":"racing"},
{"name":"project gotham racing 4","developer":"bizarre creations","publisher":"microsoft","genre":"racing"},
{"name":"project zoo","developer":"unknown","publisher":"bam enterainment","genre":"action adventure"},
{"name":"project zoo","developer":"nintendo","publisher":"nintendo","genre":"platformer"},
{"name":"psychonauts","developer":"double fine","publisher":"majesco entertainment","genre":"platformer"},
{"name":"psychonauts 2","developer":"double fine","publisher":"xbox game studios","genre":"action adventure"},
{"name":"pure","developer":"black rock studio","publisher":"disney interactive studios","genre":"racing"},
{"name":"quantum break","developer":"remedy","publisher":"xbox game studios","genre":"action adventure"},
{"name":"quantum of solace","developer":"treyarch","publisher":"unknown","genre":"fps"},
{"name":"quantum rush champions","developer":"frictonal games","publisher":"frictonal games","genre":"racing"},
{"name":"qube 2","developer":"traped nerve","publisher":"toxic games","genre":"puzzle"},
{"name":"rage","developer":"id tech","publisher":"bethesda","genre":"fps"},
{"name":"rango","developer":"sucker punch","publisher":"sony computer entertainment","genre":"action adventure"},
{"name":"ratatouille","developer":"heavy iron studios","publisher":"thq","genre":"platformer"},
{"name":"ratchet and clank","developer":"insomniac games","publisher":"sony computer entertainment","genre":"action adventure"},
{"name":"ratchet and clank 2","developer":"insomniac games","publisher":"sony computer entertainment","genre":"action adventure"},
{"name":"ratchet and clank 3","developer":"insomniac games","publisher":"sony computer entertainment","genre":"action adventure"},
{"name":"ratchet and clank into the nexus","developer":"insomniac games","publisher":"sony computer entertainment","genre":"action adventure"},
{"name":"ratchet and clank quest for booty","developer":"insomniac games","publisher":"sony computer entertainment","genre":"action adventure"},
{"name":"ratchet and clank tools of destruction","developer":"insomniac games","publisher":"sony computer entertainment","genre":"action adventure"},
{"name":"rayman origins","developer":"ubisoft","publisher":"ubisoft","genre":"platformer"},
{"name":"red dead redemption goty","developer":"sony","publisher":"sony computer entertainment","genre":"action adventure"},
{"name":"red faction armageddon","developer":"techland","publisher":"deep silver","genre":"survival horror"},
{"name":"redout","developer":"34bigthings","publisher":"34bigthings","genre":"racing"},
{"name":"remember me","developer":"dont nod","publisher":"capcom","genre":"action adventure"},
{"name":"remnant from the ashes","developer":"gunfire games","publisher":"perfect world","genre":"action adventure"},
{"name":"resident evil 4 hd","developer":"capcom","publisher":"capcom","genre":"action adventure"},
{"name":"resident evil 5 gold edition","developer":"capcom","publisher":"capcom","genre":"action adventure"},
{"name":"resident evil 6","developer":"capcom","publisher":"capcom","genre":"platformer"},
{"name":"resident evil outbreak","developer":"capcom","publisher":"capcom","genre":"action adventure"},
{"name":"resident evil revelations","developer":"capcom","publisher":"capcom","genre":"action adventure"},
{"name":"resident evil revelations 2","developer":"black box","publisher":"capcom","genre":"action adventure"},
{"name":"return to mysterious island","developer":"kheops","publisher":"the adventure company","genre":"adventure"},
{"name":"return to mysterious island 2","developer":"kheops","publisher":"microids","genre":"adventure"},
{"name":"rez","developer":"sega","publisher":"sony computer entertainment","genre":"shooter"},
{"name":"ride","developer":"milestone","publisher":"milestone","genre":"racing"},
{"name":"rime","developer":"tequila","publisher":"sony computer entertainment","genre":"action adventure"},
{"name":"riptide gp renegade","developer":"eidos","publisher":"square enix","genre":"racing"},
{"name":"rise of the agronauts","developer":"infinty ward","publisher":"codemasters","genre":"rpg"},
{"name":"rise to honor","developer":"nintendo","publisher":"nintendo","genre":"action adventure"},
{"name":"road to india","developer":"microids","publisher":"microids","genre":"adventure"},
{"name":"robots","developer":"eurocom","publisher":"sierra","genre":"platformer"},
{"name":"rochard","developer":"recoil games","publisher":"daybreak game company","genre":"platformer"},
{"name":"rogue galaxy","developer":"sony","publisher":"sony computer entertainment","genre":"rpg"},
{"name":"roki","developer":"polygon treehouse","publisher":"polygon treehouse","genre":"adventure"},
{"name":"rule of rose","developer":"sony","publisher":"505 games","genre":"survival horror"},
{"name":"rumble roses","developer":"namco","publisher":"konami digital entertainment","genre":"fighter"},
{"name":"runaway","developer":"pendulo studios","publisher":"focus home interactive","genre":"adventure"},
{"name":"runaway 2","developer":"pendulo studios","publisher":"focus home interactive","genre":"adventure"},
{"name":"runaway 3","developer":"pendulo studios","publisher":"focus home interactive","genre":"adventure"},
{"name":"rygar","developer":"remedy","publisher":"konami digital entertainment","genre":"action adventure"},
{"name":"sable","developer":"shedworks","publisher":"raw fury","genre":"action adventure"},
{"name":"saboteur","developer":"midway","publisher":"electronic arts","genre":"action adventure"},
{"name":"salammbo","developer":"unknown","publisher":"unknown","genre":"adventure"},
{"name":"sam and max - abe lincoln must die","developer":"telltale games","publisher":"telltale games","genre":"adventure"},
{"name":"sam and max - bright side of the moon","developer":"telltale games","publisher":"telltale games","genre":"adventure"},
{"name":"sam and max - culture shock","developer":"telltale games","publisher":"telltale games","genre":"adventure"},
{"name":"sam and max - reality 2.0","developer":"telltale games","publisher":"telltale games","genre":"adventure"},
{"name":"sam and max - season two - episode five","developer":"telltale games","publisher":"telltale games","genre":"adventure"},
{"name":"sam and max - season two - episode one","developer":"telltale games","publisher":"telltale games","genre":"adventure"},
{"name":"sam and max - season two - episode three","developer":"telltale games","publisher":"telltale games","genre":"adventure"},
{"name":"sam and max - situation comedy","developer":"telltale games","publisher":"telltale games","genre":"adventure"},
{"name":"sam and max - the mole, the mob and the meatball","developer":"telltale games","publisher":"telltale games","genre":"adventure"},
{"name":"sam and max the devils playhouse","developer":"telltale games","publisher":"telltale games","genre":"adventure"},
{"name":"scarlet nexus","developer":"bandai namco","publisher":"bandai namco entertainment","genre":"rpg"},
{"name":"scooby doo and the spooky swamp","developer":"torus games","publisher":"warner bros. interactive entertainment","genre":"platformer"},
{"name":"scooby doo first frights","developer":"torus games","publisher":"warner bros. interactive entertainment","genre":"action adventure"},
{"name":"scooby doo first frights","developer":"torus games","publisher":"warner bros. interactive entertainment","genre":"action adventure"},
{"name":"scratches","developer":"nucleosys","publisher":"got game entertainment","genre":"adventure"},
{"name":"sebastien loeb rally","developer":"milestone","publisher":"unknown","genre":"racing"},
{"name":"secret files 2","developer":"animation arts","publisher":"deep silver","genre":"adventure"},
{"name":"secret files 3","developer":"animation arts","publisher":"deep silver","genre":"adventure"},
{"name":"secret files tunguska","developer":"animation arts","publisher":"deep silver","genre":"adventure"},
{"name":"secret weapons over normandy","developer":"totally games","publisher":"lucas arts","genre":"flightsim"},
{"name":"sega rally revo","developer":"sega","publisher":"sega","genre":"racing"},
{"name":"sekiro shadows die twice","developer":"from software","publisher":"activision","genre":"action adventure"},
{"name":"shadow of rome","developer":"capcom","publisher":"capcom","genre":"action adventure"},
{"name":"shadow of the colossus","developer":"sony","publisher":"sony computer entertainment","genre":"action adventure"},
{"name":"shaun white snowboarding","developer":"ubisoft","publisher":"ubisoft","genre":"sports"},
{"name":"shenmue part i","developer":"unknown","publisher":"sega","genre":"action adventure"},
{"name":"sherlock holmes - chapter one","developer":"frogwares","publisher":"frogwares","genre":"action adventure"},
{"name":"sherlock holmes - crimes and punishments","developer":"frogwares","publisher":"frogwares","genre":"adventure"},
{"name":"sherlock holmes - testament of sherlock holmes","developer":"frogwares","publisher":"focus home interactive","genre":"adventure"},
{"name":"sherlock holmes - the awakened","developer":"frogwares","publisher":"focus home interactive","genre":"action adventure"},
{"name":"sherlock holmes - the case of the silver earring","developer":"frogwares","publisher":"focus home interactive","genre":"adventure"},
{"name":"sherlock holmes - the devils daughter","developer":"frogwares","publisher":"big ben interactive","genre":"action adventure"},
{"name":"sherlock holmes - versus arsene lupin","developer":"frogwares","publisher":"focus home interactive","genre":"action adventure"},
{"name":"sherlock holmes vs jack the ripper","developer":"frogwares","publisher":"focus home interactive","genre":"adventure"},
{"name":"shinobi","developer":"sony","publisher":"sega","genre":"action adventure"},
{"name":"signalis","developer":"rose-engine","publisher":"playism","genre":"action adventure"},
{"name":"silent hill 2","developer":"team silent","publisher":"konami digital entertainment","genre":"survival horror"},
{"name":"silent hill 3","developer":"konami","publisher":"konami digital entertainment","genre":"survival horror"},
{"name":"silent hill 4","developer":"konami","publisher":"konami digital entertainment","genre":"survival horror"},
{"name":"silent hill home coming","developer":"konami","publisher":"konami digital entertainment","genre":"survival horror"},
{"name":"silent hill origins","developer":"sony","publisher":"sony computer entertainment","genre":"survival horror"},
{"name":"sin and punishment 2","developer":"nintendo","publisher":"nintendo","genre":"action adventure"},
{"name":"singularity","developer":"raven software","publisher":"activision","genre":"fps"},
{"name":"sinking island","developer":"white birds productions","publisher":"microids","genre":"adventure"},
{"name":"slipheed","developer":"sony","publisher":"sony computer entertainment","genre":"shooter"},
{"name":"sly cooper","developer":"sucker punch","publisher":"sony computer entertainment","genre":"action adventure"},
{"name":"sly cooper 2 band of thieves","developer":"sucker punch","publisher":"sony computer entertainment","genre":"action adventure"},
{"name":"sly cooper 3 honour among thieves","developer":"sucker punch","publisher":"sony computer entertainment","genre":"action adventure"},
{"name":"sly cooper thieves in time","developer":"sucker punch","publisher":"sony computer entertainment","genre":"action adventure"},
{"name":"solar ash","developer":"heart machine","publisher":"annapurna interactive","genre":"action adventure"},
{"name":"soma","developer":"frictional games","publisher":"frictional games","genre":"adventure"},
{"name":"soul blade","developer":"namco","publisher":"sony computer entertainment","genre":"fighter"},
{"name":"soulcalibur","developer":"namco","publisher":"bandai namco entertainment","genre":"fighter"},
{"name":"soulcalibur 2","developer":"nintendo","publisher":"nintendo","genre":"fighter"},
{"name":"soulcalibur 3","developer":"sony","publisher":"sony computer entertainment","genre":"fighter"},
{"name":"soulcalibur v","developer":"sony","publisher":"bandai namco entertainment","genre":"action adventure"},
{"name":"soulstice","developer":"reply game studios","publisher":"modus games","genre":"action adventure"},
{"name":"spec ops the line","developer":"unknown","publisher":"take-two interactive","genre":"action adventure"},
{"name":"sphinx and the cursed mummy","developer":"thq nordic","publisher":"thq","genre":"action adventure"},
{"name":"sphinx and the cursed mummy","developer":"eurocom","publisher":"thq","genre":"action adventure"},
{"name":"spiderman shatterd dimensions","developer":"beenox","publisher":"activision","genre":"action adventure"},
{"name":"spiderman the movie","developer":"treyarch","publisher":"activision","genre":"action adventure"},
{"name":"splashdown","developer":"deadelic","publisher":"atari","genre":"action adventure"},
{"name":"splinter cell blacklist","developer":"ubisoft","publisher":"ubisoft","genre":"action adventure"},
{"name":"splinter cell chaos theory","developer":"ubisoft","publisher":"ubisoft","genre":"action adventure"},
{"name":"splinter cell conviction","developer":"ubisoft","publisher":"ubisoft","genre":"action adventure"},
{"name":"splinter cell double agent","developer":"ubisoft","publisher":"ubisoft","genre":"action adventure"},
{"name":"ssx 3","developer":"ea big","publisher":"electronic arts","genre":"sports"},
{"name":"ssx ps3","developer":"ea big","publisher":"electronic arts","genre":"action adventure"},
{"name":"stained","developer":"unknown","publisher":"real axis software","genre":"platformer"},
{"name":"star trek","developer":"digital extremes","publisher":"bandai namco entertainment","genre":"action adventure"},
{"name":"star trek resurgence","developer":"unknown","publisher":"unknown","genre":"action adventure"},
{"name":"star wars episode i racer","developer":"lucas arts","publisher":"lucas arts","genre":"racing"},
{"name":"star wars jedi fallen order","developer":"respawn","publisher":"electronic arts","genre":"action adventure"},
{"name":"star wars rogue squadron 3 rebel strike","developer":"lucas arts","publisher":"lucas arts","genre":"action adventure"},
{"name":"starfox adventures","developer":"nintendo","publisher":"nintendo","genre":"action adventure"},
{"name":"starwars battlefront","developer":"techland","publisher":"deep silver","genre":"fps"},
{"name":"state of mind","developer":"through line","publisher":"daedalic entertainment","genre":"adventure"},
{"name":"steelrising","developer":"spyders","publisher":"nacon","genre":"action adventure"},
{"name":"still life","developer":"microids","publisher":"microids","genre":"adventure"},
{"name":"still life 2","developer":"microids","publisher":"microids","genre":"adventure"},
{"name":"strange brigade","developer":"rebellion","publisher":"rebellion","genre":"action adventure"},
{"name":"stranglehold","developer":"midway games","publisher":"midway games","genre":"action adventure"},
{"name":"submerged","developer":"uppercut games","publisher":"uppercut games","genre":"action adventure"},
{"name":"submerged hidden depths","developer":"uppercut games","publisher":"uppercut games","genre":"action adventure"},
{"name":"super mario 3d world","developer":"nintendo","publisher":"nintendo","genre":"platformer"},
{"name":"super mario galaxy 2","developer":"nintendo","publisher":"nintendo","genre":"action adventure"},
{"name":"super mario odyssey","developer":"nintendo","publisher":"nintendo","genre":"action adventure"},
{"name":"super mario sunshine","developer":"nintendo","publisher":"nintendo","genre":"action adventure"},
{"name":"super monkey ball","developer":"nintendo","publisher":"atari","genre":"action adventure"},
{"name":"superbike 2009","developer":"aspyr","publisher":"unknown","genre":"racing"},
{"name":"syberia","developer":"microids","publisher":"microids","genre":"adventure"},
{"name":"syberia 2","developer":"microids","publisher":"unknown","genre":"adventure"},
{"name":"syberia 3","developer":"wingbirds","publisher":"microids","genre":"adventure"},
{"name":"syberia 4 the world before","developer":"microids","publisher":"microids","genre":"adventure"},
{"name":"syberia complete collection","developer":"sony","publisher":"sony computer entertainment","genre":"action adventure"},
{"name":"tak and the power of juju","developer":"deadelic","publisher":"thq","genre":"action adventure"},
{"name":"tales of arise","developer":"bandai namco","publisher":"bandai namco entertainment","genre":"rpg"},
{"name":"tales of the neon sea","developer":"palm pioneer","publisher":"blue brain","genre":"adventure"},
{"name":"tchia","developer":"unknown","publisher":"unknown","genre":"action adventure"},
{"name":"terminator salvation","developer":"evolved games","publisher":"warner bros. interactive entertainment","genre":"action adventure"},
{"name":"test drive unlimited 2","developer":"eden games","publisher":"atari","genre":"racing"},
{"name":"testament of sin","developer":"unknown","publisher":"unknown","genre":"adventure"},
{"name":"the abbey","developer":"unknown","publisher":"unknown","genre":"adventure"},
{"name":"the adventures of tintin - the secret of the unicorn","developer":"ubisoft","publisher":"ubisoft","genre":"action adventure"},
{"name":"the amazing spiderman 2","developer":"benox","publisher":"activision","genre":"action adventure"},
{"name":"the book of unwritten tales critter chronicles","developer":"king art games","publisher":"nordic games","genre":"adventure"},
{"name":"the cave","developer":"double fine","publisher":"sega","genre":"platformer"},
{"name":"the da vinici code","developer":"unknown","publisher":"take-two interactive","genre":"adventure"},
{"name":"the dark eye - chains of satinav","developer":"remedy","publisher":"sega","genre":"adventure"},
{"name":"the darkness 2","developer":"unknown","publisher":"take-two interactive","genre":"fps"},
{"name":"the egyptian prophecy","developer":"unknown","publisher":"unknown","genre":"adventure"},
{"name":"the elder scrolls v skyrim","developer":"bethesda","publisher":"bethesda","genre":"action adventure"},
{"name":"the evil within","developer":"tango gameworks","publisher":"bethesda","genre":"survival horror"},
{"name":"the evil within 2","developer":"tango gameworks","publisher":"bethesda","genre":"action adventure"},
{"name":"the fidelio incident","developer":"tequilla","publisher":"microsoft","genre":"action adventure"},
{"name":"the girl and the robot","developer":"indy","publisher":"indy","genre":"platformer"},
{"name":"the golden compass","developer":"shiny entertainment","publisher":"sega","genre":"action adventure"},
{"name":"the great escape","developer":"ocean software","publisher":"ocean software","genre":"action adventure"},
{"name":"the house of da vinci","developer":"blue brain games","publisher":"blue brain games","genre":"adventure"},
{"name":"the house of da vinci 2","developer":"blue brain games","publisher":"blue brain games","genre":"adventure"},
{"name":"the inner world","developer":"studio fizbin","publisher":"headup games","genre":"adventure"},
{"name":"the last remenant","developer":"aspyr","publisher":"unknown","genre":"rpg"},
{"name":"the last story","developer":"deadelic","publisher":"nintendo","genre":"rpg"},
{"name":"the legend of zelda breath of the wild","developer":"nintendo","publisher":"nintendo","genre":"action adventure"},
{"name":"the legend of zelda skyward sword","developer":"nintendo","publisher":"nintendo","genre":"action adventure"},
{"name":"the legend of zelda the windwaker hd","developer":"sony","publisher":"nintendo","genre":"action adventure"},
{"name":"the legend of zelda twilight princess hd","developer":"nintendo","publisher":"nintendo","genre":"action adventure"},
{"name":"the longest journey","developer":"funcom","publisher":"ubisoft","genre":"adventure"},
{"name":"the lord of the rings - the two towers","developer":"nintendo","publisher":"nintendo","genre":"action adventure"},
{"name":"the moment of silence","developer":"house of tales","publisher":"digital jesters","genre":"adventure"},
{"name":"the next big thing","developer":"pendulo studios","publisher":"focus home interactive","genre":"adventure"},
{"name":"the night of the rabbit","developer":"daedalic entertainment","publisher":"daedalic entertainment","genre":"adventure"},
{"name":"the pathless","developer":"giant squid","publisher":"annapurna interactive","genre":"action adventure"},
{"name":"the perils of man","developer":"black box","publisher":"microsoft","genre":"adventure"},
{"name":"the raven - legacy of a master thief","developer":"unknown","publisher":"deep silver","genre":"adventure"},
{"name":"the room","developer":"fireproof studios","publisher":"fireproof studios","genre":"adventure"},
{"name":"the room four","developer":"fireproof studios","publisher":"fireproof studios","genre":"adventure"},
{"name":"the room three","developer":"fireproof studios","publisher":"fireproof studios","genre":"adventure"},
{"name":"the room two","developer":"fireproof studios","publisher":"fireproof studios","genre":"adventure"},
{"name":"the secrets of atlantis","developer":"unknown","publisher":"nobilis","genre":"adventure"},
{"name":"the secrets of da vinci","developer":"unknown","publisher":"nobilis","genre":"adventure"},
{"name":"the sinking city","developer":"frogwares","publisher":"nacon","genre":"action adventure"},
{"name":"the solus project","developer":"hourences","publisher":"teotl studios","genre":"adventure"},
{"name":"the surge","developer":"deck13 interactive","publisher":"focus home interactive","genre":"action adventure"},
{"name":"the thing","developer":"unknown","publisher":"vivendi games","genre":"action adventure"},
{"name":"the vanishing of ethan carter","developer":"astronauts","publisher":"bandai namco entertainment","genre":"adventure"},
{"name":"the walking dead survival instinct","developer":"unknown","publisher":"activision","genre":"survival horror"},
{"name":"the witcher 2 enhanced edition","developer":"cd project red","publisher":"unknown","genre":"rpg"},
{"name":"the witcher 3 wild hunt","developer":"cd project red","publisher":"bandai namco entertainment","genre":"rpg"},
{"name":"titanfall 2","developer":"respawn entertainment","publisher":"electronic arts","genre":"fps"},
{"name":"tokyo highway challenge 2","developer":"crave entertainment","publisher":"sega","genre":"racing"},
{"name":"tomb raider - anniversary edition","developer":"crystal dynamics","publisher":"eidos","genre":"action adventure"},
{"name":"tomb raider - dagger of xian","developer":"bethesda","publisher":"bethesda","genre":"action adventure"},
{"name":"tomb raider - guardian of light","developer":"crystal dynamics","publisher":"eidos","genre":"action adventure"},
{"name":"tomb raider - legend","developer":"crystal dynamics","publisher":"eidos","genre":"action adventure"},
{"name":"tomb raider - rise","developer":"crystal dynamics","publisher":"square enix","genre":"action adventure"},
{"name":"tomb raider - shadow","developer":"crystal dynamics","publisher":"square enix","genre":"action adventure"},
{"name":"tomb raider - underworld","developer":"crystal dynamics","publisher":"eidos","genre":"action adventure"},
{"name":"tomb raider 2013","developer":"crystal dynamics","publisher":"square enix","genre":"action adventure"},
{"name":"toonstrk","developer":"unknown","publisher":"virgin interactive entertainment","genre":"adventure"},
{"name":"toonstrk - readme","developer":"unknown","publisher":"unknown","genre":"adventure"},
{"name":"toonstrk - univesa","developer":"unknown","publisher":"unknown","genre":"adventure"},
{"name":"toukiden 2","developer":"w omega","publisher":"tecmo koei","genre":"action adventure"},
{"name":"transformers fall of cybertron","developer":"unknown","publisher":"activision","genre":"action adventure"},
{"name":"transformers war for cybertron","developer":"activision","publisher":"activision","genre":"action adventure"},
{"name":"treasure island","developer":"unknown","publisher":"dreamcatcher interactive","genre":"adventure"},
{"name":"trek to yomi","developer":"unknown","publisher":"unknown","genre":"action adventure"},
{"name":"trine","developer":"frozenbyte","publisher":"southpeak games","genre":"platformer"},
{"name":"tt isle of man ride on the edge 3","developer":"kyton","publisher":"nanco","genre":"racing"},
{"name":"tunic","developer":"isometricorp games","publisher":"finji","genre":"action adventure"},
{"name":"turning point fall of liberty","developer":"ninja theory","publisher":"konami digital entertainment","genre":"action adventure"},
{"name":"uncharted 2 among thieves game of the year edition","developer":"naughty dog","publisher":"sony computer entertainment","genre":"action adventure"},
{"name":"uncharted 3 drakes deception","developer":"naughty dog","publisher":"sony computer entertainment","genre":"action adventure"},
{"name":"uncharted drakes fortune","developer":"naughty dog","publisher":"sony computer entertainment","genre":"action adventure"},
{"name":"uncharted legacy of thieves collection","developer":"naughty dog","publisher":"sony computer entertainment","genre":"action adventure"},
{"name":"undercover operation wintersun","developer":"unknown","publisher":"anaconda","genre":"adventure"},
{"name":"up","developer":"heavy iron studios","publisher":"thq","genre":"platformer"},
{"name":"valkyrie elysium","developer":"soleil","publisher":"square enix","genre":"action adventure"},
{"name":"van helsing","developer":"sony","publisher":"activision","genre":"action adventure"},
{"name":"velvet assassin","developer":"replay studios","publisher":"southpeak games","genre":"action adventure"},
{"name":"venetica gold","developer":"nordic games","publisher":"dtp entertainment","genre":"rpg"},
{"name":"voodoo vince remastered","developer":"microsoft","publisher":"microsoft","genre":"platformer"},
{"name":"voyage","developer":"kheops","publisher":"the adventure company","genre":"adventure"},
{"name":"wallace and gromit 01","developer":"telltale","publisher":"unknown","genre":"adventure"},
{"name":"wanted","developer":"revistronic","publisher":"nobilis","genre":"adventure"},
{"name":"wanted 2","developer":"revitronic","publisher":"nobilis","genre":"adventure"},
{"name":"wanted weapons of fate","developer":"aspyr","publisher":"unknown","genre":"action adventure"},
{"name":"watch dogs","developer":"ubisoft","publisher":"ubisoft","genre":"action adventure"},
{"name":"westmark manor","developer":"blue brain","publisher":"blue brain","genre":"adventure"},
{"name":"whispered world","developer":"deep silver","publisher":"ubisoft","genre":"adventure"},
{"name":"whiteout","developer":"unknown","publisher":"konami digital entertainment","genre":"racing"},
{"name":"wings of prey","developer":"777 studios","publisher":"gaijin entertainment","genre":"flightsim"},
{"name":"wipeout","developer":"psygnosis","publisher":"sony computer entertainment","genre":"racing"},
{"name":"wipeout 2097","developer":"psygnosis","publisher":"sony computer entertainment","genre":"racing"},
{"name":"wipeout 3","developer":"psygnosis","publisher":"sony computer entertainment","genre":"racing"},
{"name":"wipeout 3 special edition","developer":"psygnosis","publisher":"sony computer entertainment","genre":"racing"},
{"name":"wipeout fusion","developer":"sony","publisher":"sony computer entertainment","genre":"racing"},
{"name":"wipeout hd fury","developer":"sony","publisher":"sony computer entertainment","genre":"racing"},
{"name":"wipeout pulse","developer":"sony","publisher":"sony computer entertainment","genre":"racing"},
{"name":"wolfenstein","developer":"ravensoft","publisher":"activision","genre":"action adventure"},
{"name":"wolfenstein 2","developer":"machine games","publisher":"bethesda","genre":"fps"},
{"name":"wolverine","developer":"raven","publisher":"activision","genre":"action adventure"},
{"name":"world rally car championship 3","developer":"evolution","publisher":"sony computer entertainment","genre":"action adventure"},
{"name":"wrc 10","developer":"kylotonn","publisher":"nacon","genre":"racing"},
{"name":"wrc 3","developer":"evolution studios","publisher":"sony computer entertainment","genre":"racing"},
{"name":"wrc 3","developer":"milestone","publisher":"black beans","genre":"racing"},
{"name":"wrc 4","developer":"kylotonn","publisher":"nacon","genre":"racing"},
{"name":"wrc 5","developer":"big ben interactive","publisher":"nacon","genre":"racing"},
{"name":"wrc 6","developer":"kylotonn","publisher":"nacon","genre":"racing"},
{"name":"wrc 7","developer":"kylotonn","publisher":"nacon","genre":"racing"},
{"name":"wrc 8","developer":"kylotonn","publisher":"nacon","genre":"racing"},
{"name":"wrc 9","developer":"kylotonn","publisher":"nacon","genre":"racing"},
{"name":"wrc rally evolved","developer":"sony","publisher":"sony computer entertainment","genre":"racing"},
{"name":"xenoblade chronicles x","developer":"sony","publisher":"nintendo","genre":"action adventure"},
{"name":"xg3 extreme g racing","developer":"akklaim","publisher":"akklaim","genre":"racing"},
{"name":"xgra extreme g racing association","developer":"nintendo","publisher":"nintendo","genre":"racing"},
{"name":"xuan-yuan sword 7","developer":"polygon treehouse","publisher":"polygon treehouse","genre":"action adventure"},
{"name":"yesterday","developer":"pendulo studios","publisher":"focus home interactive","genre":"adventure"},
{"name":"yonder the cloud catcher chronicles","developer":"prideful sloth","publisher":"prideful sloth","genre":"rpg"},
{"name":"youropa","developer":"through line","publisher":"square enix","genre":"puzzle"},
{"name":"zack and wiki","developer":"nintendo","publisher":"nintendo","genre":"adventure"},
{"name":"zelda the wind waker","developer":"nintendo","publisher":"nintendo","genre":"action adventure"},
{"name":"zelda twilight princess","developer":"nintendo","publisher":"nintendo","genre":"action adventure"}
]
